decoratorutilities/__init__.py
decoratorutilities/_cached.py
decoratorutilities/_checktype.py
decoratorutilities/_debug.py
decoratorutilities/_memoized.py
decoratorutilities/_mocking.py
decoratorutilities/_overload.py
decoratorutilities/_singleton.py
decoratorutilities/_timeit.py
tests/__init__.py
tests/test_checktype.py
tests/test_mocking.py
tests/test_overload.py
decoratorutilities-1.0.2.dist-info/LICENSE
decoratorutilities-1.0.2.dist-info/METADATA
decoratorutilities-1.0.2.dist-info/WHEEL
decoratorutilities-1.0.2.dist-info/top_level.txt
decoratorutilities-1.0.2.dist-info/RECORD
