Metadata-Version: 2.1
Name: decoratorutilities
Version: 1.0.2
Summary: Python library to user type guard utilities to check parameters and return type, allow function overloading and function mocking at runtime
Home-page: https://github.com/Symone95/decoratorutilities
Author: Scalamandrè Simone, Giovanni Cardamone
Author-email: simone.scalamandre@sourcesense.com, giovanni.cardamone@sourcesense.com
License: UNKNOWN
Download-URL: https://pypi.org/project/decoratorutilities/#files
Platform: UNKNOWN
Classifier: Programming Language :: Python :: 3
Classifier: License :: OSI Approved :: MIT License
Classifier: Operating System :: OS Independent
Requires-Python: >=3.7
